datameetpdf/__init__.py
datameetpdf/core/__init__.py
datameetpdf/core/report.py
datameetpdf/template/__init__.py
datameetpdf/template/basic.css
datameetpdf/template/basic_html.py
datameetpdf/util/__init__.py
datameetpdf/util/html.py
datameetpdf-0.0.9.dist-info/LICENSE
datameetpdf-0.0.9.dist-info/METADATA
datameetpdf-0.0.9.dist-info/WHEEL
datameetpdf-0.0.9.dist-info/top_level.txt
datameetpdf-0.0.9.dist-info/RECORD
