Metadata-Version: 2.1
Name: datameetpdf
Version: 0.0.9
Summary: Create PDF by using selected different data outputs
Home-page: https://github.com/quantransform/datameetpdf
Author: Jeremy Wang
Author-email: j.wang@quantransform.co.uk
License: UNKNOWN
Platform: UNKNOWN
Classifier: Programming Language :: Python :: 3
Classifier: License :: OSI Approved :: MIT License
Classifier: Operating System :: OS Independent
Requires-Python: >=3.6
License-File: LICENSE
Requires-Dist: wkhtmltopdf (==0.2)
Requires-Dist: pdfkit (==1.0.0)
Requires-Dist: pandas (>=1.0.0)
Requires-Dist: numpy (>=1.0.0)
Requires-Dist: plotly (>=5.0.0)
